ai_models_gencast/__init__.py
ai_models_gencast/_version.py
ai_models_gencast/convert.py
ai_models_gencast/input.py
ai_models_gencast/model.py
ai_models_gencast/output.py
ai_models_gencast-0.0.5.dist-info/LICENSE
ai_models_gencast-0.0.5.dist-info/METADATA
ai_models_gencast-0.0.5.dist-info/WHEEL
ai_models_gencast-0.0.5.dist-info/entry_points.txt
ai_models_gencast-0.0.5.dist-info/top_level.txt
ai_models_gencast-0.0.5.dist-info/RECORD
