Metadata-Version: 2.2
Name: ai-models-gencast
Version: 0.0.5
Summary: An ai-models plugin to run Deepmind's gencast model
Author-email: "European Centre for Medium-Range Weather Forecasts (ECMWF)" <software.support@ecmwf.int>
License:                                  Apache License
Project-URL: Repository, https://github.com/ecmwf-lab/ai-models-gencast
Keywords: ai,tools
Classifier: Development Status :: 4 - Beta
Classifier: Intended Audience :: Developers
Classifier: License :: OSI Approved :: Apache Software License
Classifier: Operating System :: OS Independent
Classifier: Programming Language :: Python :: 3 :: Only
Classifier: Programming Language :: Python :: 3.9
Classifier: Programming Language :: Python :: 3.10
Classifier: Programming Language :: Python :: 3.11
Classifier: Programming Language :: Python :: 3.12
Classifier: Programming Language :: Python :: Implementation :: CPython
Classifier: Programming Language :: Python :: Implementation :: PyPy
Requires-Python: >=3.10
License-File: LICENSE
Requires-Dist: ai-models>=0.7.4
Requires-Dist: dm-tree
Requires-Dist: dm-haiku
Requires-Dist: xarray<=2024.11.0
Provides-Extra: dev
Requires-Dist: pre-commit; extra == "dev"
